{"blogName":"The Little Engineer Who Codes","blogAuthor":"Alyssa Rosenzweig","gitRemote":"https://github.com/bobbybee/bobbybee.github.io.git","creationDate":"2015-03-21T01:03:03.090Z","header":{"type":"include","path":"header.html"},"footer":{"type":"include","path":"footer.html"},"post":{"type":"include","path":"post.html"},"index":{"type":"include","path":"index.html"},"style":"includes/style.css","posts":[{"title":"Hello, World!","subtitle":"How ridiculous this saying is, and why I'll say it anyway","fileId":"Hello,-World!","content":{"type":"include","path":"Hello,-World!.md"},"date":"2015-03-21T01:06:06.308Z"}],"raws":[]}